CHANGELOG.md
CLA.md
CODE_OF_CONDUCT.md
CONTRIBUTING.md
MANIFEST.in
README.md
RELEASE_NOTES.md
requirements-test.txt
requirements.txt
setup.cfg
setup.py
africunia/__init__.py
africunia/account.py
africunia/amount.py
africunia/asset.py
africunia/bitshares.py
africunia/block.py
africunia/blockchain.py
africunia/blockchainobject.py
africunia/committee.py
africunia/dex.py
africunia/exceptions.py
africunia/genesisbalance.py
africunia/htlc.py
africunia/instance.py
africunia/market.py
africunia/memo.py
africunia/message.py
africunia/notify.py
africunia/price.py
africunia/proposal.py
africunia/storage.py
africunia/transactionbuilder.py
africunia/utils.py
africunia/vesting.py
africunia/wallet.py
africunia/witness.py
africunia/worker.py
africunia.egg-info/PKG-INFO
africunia.egg-info/SOURCES.txt
africunia.egg-info/dependency_links.txt
africunia.egg-info/requires.txt
africunia.egg-info/top_level.txt
africunia/aio/__init__.py
africunia/aio/account.py
africunia/aio/amount.py
africunia/aio/asset.py
africunia/aio/bitshares.py
africunia/aio/block.py
africunia/aio/blockchain.py
africunia/aio/blockchainobject.py
africunia/aio/committee.py
africunia/aio/dex.py
africunia/aio/genesisbalance.py
africunia/aio/htlc.py
africunia/aio/instance.py
africunia/aio/market.py
africunia/aio/memo.py
africunia/aio/message.py
africunia/aio/price.py
africunia/aio/proposal.py
africunia/aio/transactionbuilder.py
africunia/aio/vesting.py
africunia/aio/wallet.py
africunia/aio/witness.py
africunia/aio/worker.py
africuniaapi/__init__.py
africuniaapi/bitsharesnoderpc.py
africuniaapi/exceptions.py
africuniaapi/websocket.py
africuniaapi/aio/bitsharesnoderpc.py
africuniabase/__init__.py
africuniabase/account.py
africuniabase/asset_permissions.py
africuniabase/bip38.py
africuniabase/chains.py
africuniabase/memo.py
africuniabase/objects.py
africuniabase/objecttypes.py
africuniabase/operationids.py
africuniabase/operations.py
africuniabase/signedtransactions.py
africuniabase/transactions.py