Metadata-Version: 1.2
Name: africunia
Version: 0.7.1
Summary: Python library for africunia
Home-page: https://github.com/africunia/python-africunia
Author: Fabian Schuh
Author-email: Fabian@chainsquad.com
Maintainer: Fabian Schuh
Maintainer-email: Fabian@chainsquad.com
License: UNKNOWN
Download-URL: https://github.com/africunia/python-africunia/tarball/0.7.1
Keywords: africunia,library,api,rpc
Platform: UNKNOWN
Classifier: License :: OSI Approved :: MIT License
Classifier: Operating System :: OS Independent
Classifier: Programming Language :: Python :: 3
Classifier: Development Status :: 3 - Alpha
Classifier: Intended Audience :: Developers
Classifier: Intended Audience :: Financial and Insurance Industry
Classifier: Topic :: Office/Business :: Financial
